argdec.py
argdec-0.2.2.dist-info/licenses/LICENSE
argdec-0.2.2.dist-info/METADATA
argdec-0.2.2.dist-info/WHEEL
argdec-0.2.2.dist-info/top_level.txt
argdec-0.2.2.dist-info/RECORD
