Metadata-Version: 2.4
Name: argdec
Version: 0.2.2
Summary: A decorator-based, declarative interface to Python's argparse for building hierarchical CLI applications.
Author-email: Shakeeb Alireza <me@example.com>
License-Expression: MIT
Keywords: argparse,cli,command-line,declarative,decorator
Classifier: Development Status :: 4 - Beta
Classifier: Intended Audience :: Developers
Classifier: Programming Language :: Python :: 3
Classifier: Programming Language :: Python :: 3.7
Classifier: Programming Language :: Python :: 3.8
Classifier: Programming Language :: Python :: 3.9
Classifier: Programming Language :: Python :: 3.10
Classifier: Programming Language :: Python :: 3.11
Classifier: Programming Language :: Python :: 3.12
Classifier: Programming Language :: Python :: 3.13
Classifier: Topic :: Software Development :: Libraries :: Python Modules
Requires-Python: >=3.7
License-File: LICENSE
Dynamic: license-file
